pyrez/__init__.py
pyrez/__main__.py
pyrez/__version__.py
pyrez/command_line.py
pyrez/events.py
pyrez/api/API.py
pyrez/api/APIBase.py
pyrez/api/BaseSmitePaladins.py
pyrez/api/PaladinsAPI.py
pyrez/api/RealmRoyaleAPI.py
pyrez/api/SmiteAPI.py
pyrez/api/StatusPageAPI.py
pyrez/api/__init__.py
pyrez/enumerations/AvatarPaladins.py
pyrez/enumerations/Champions.py
pyrez/enumerations/Classes.py
pyrez/enumerations/Endpoint.py
pyrez/enumerations/Enum.py
pyrez/enumerations/Format.py
pyrez/enumerations/Gods.py
pyrez/enumerations/Input.py
pyrez/enumerations/ItemType.py
pyrez/enumerations/Language.py
pyrez/enumerations/PaladinsLinks.py
pyrez/enumerations/Platform.py
pyrez/enumerations/PlatformType.py
pyrez/enumerations/PortalId.py
pyrez/enumerations/Queue.py
pyrez/enumerations/QueuePaladins.py
pyrez/enumerations/QueueRealmRoyale.py
pyrez/enumerations/QueueSmite.py
pyrez/enumerations/Region.py
pyrez/enumerations/Status.py
pyrez/enumerations/Tier.py
pyrez/enumerations/__init__.py
pyrez/exceptions/DailyLimit.py
pyrez/exceptions/Deprecated.py
pyrez/exceptions/IdOrAuthEmpty.py
pyrez/exceptions/InvalidArgument.py
pyrez/exceptions/MatchException.py
pyrez/exceptions/NoResult.py
pyrez/exceptions/NotFound.py
pyrez/exceptions/NotSupported.py
pyrez/exceptions/PaladinsOnly.py
pyrez/exceptions/PlayerNotFound.py
pyrez/exceptions/PrivatePlayer.py
pyrez/exceptions/PyrezException.py
pyrez/exceptions/RealmRoyaleOnly.py
pyrez/exceptions/RequestError.py
pyrez/exceptions/ServiceUnavailable.py
pyrez/exceptions/SessionLimit.py
pyrez/exceptions/SmiteOnly.py
pyrez/exceptions/UnexpectedException.py
pyrez/exceptions/WrongCredentials.py
pyrez/exceptions/__init__.py
pyrez/logging/__init__.py
pyrez/logging/colorizing_stream_handler.py
pyrez/logging/standard_error_handler.py
pyrez/models/APIResponse.py
pyrez/models/APIResponseBase.py
pyrez/models/Ability.py
pyrez/models/BaseMatchDetail.py
pyrez/models/DataUsed.py
pyrez/models/DemoDetails.py
pyrez/models/EsportProLeague.py
pyrez/models/Friend.py
pyrez-1.1.1.1.dist-info/LICENSE
pyrez-1.1.1.1.dist-info/METADATA
pyrez-1.1.1.1.dist-info/WHEEL
pyrez-1.1.1.1.dist-info/entry_points.txt
pyrez-1.1.1.1.dist-info/top_level.txt
pyrez-1.1.1.1.dist-info/RECORD
