Metadata-Version: 2.1
Name: pyrez
Version: 1.1.1.1
Summary: An open-source wrapper for Hi-Rez Studios API (Paladins, Realm Royale, and Smite), written in Python.
Home-page: https://github.com/luissilva1044894/pyrez
Author: Luis (Lugg) Gustavo
Author-email: the.nonsocial@gmail.com
Maintainer: Luis (Lugg) Gustavo
Maintainer-email: the.nonsocial@gmail.com
License: MIT
Download-URL: https://github.com/luissilva1044894/pyrez/archive/1.1.1.1.tar.gz
Project-URL: Documentation, https://pyrez.readthedocs.io/en/stable/
Project-URL: Tracker, https://github.com/luissilva1044894/pyrez/issues
Project-URL: Say Thanks!, https://saythanks.io/to/luissilva1044894
Project-URL: Source, https://github.com/luissilva1044894/pyrez
Keywords: pyrez,hirez,hi-rez,smite,paladins,realmapi,open-source,api,wrapper,library,python,api-wrapper,paladins-api,smitegame,smiteapi,realm-api,realm-royale,python3,python-3,python-3-6
Platform: any
Classifier: Development Status :: 5 - Production/Stable
Classifier: Intended Audience :: Developers
Classifier: License :: OSI Approved :: MIT License
Classifier: Natural Language :: English
Classifier: Operating System :: OS Independent
Classifier: Programming Language :: Python
Classifier: Programming Language :: Python :: 2
Classifier: Programming Language :: Python :: 2.7
Classifier: Programming Language :: Python :: 3
Classifier: Programming Language :: Python :: 3.5
Classifier: Programming Language :: Python :: 3.6
Classifier: Programming Language :: Python :: 3.7
Classifier: Programming Language :: Python :: 3.8
Classifier: Programming Language :: Python :: 3.9
Classifier: Programming Language :: Python :: Implementation :: CPython
Classifier: Programming Language :: Python :: Implementation :: PyPy
Classifier: Topic :: Software Development
Classifier: Topic :: Software Development :: Libraries
Classifier: Topic :: Software Development :: Libraries :: Python Modules
Classifier: Topic :: Utilities
Requires-Python: >=2.7,!=3.0.*,!=3.1.*,!=3.2.*,!=3.3.*,!=3.4.*,<4
Provides-Extra: dev
Provides-Extra: docs
Provides-Extra: httpx
